spaceone/__init__.py
spaceone/identity/__init__.py
spaceone/identity/api/__init__.py
spaceone/identity/api/v1/__init__.py
spaceone/identity/api/v1/api_key.py
spaceone/identity/api/v1/authorization.py
spaceone/identity/api/v1/domain.py
spaceone/identity/api/v1/domain_owner.py
spaceone/identity/api/v1/endpoint.py
spaceone/identity/api/v1/policy.py
spaceone/identity/api/v1/project.py
spaceone/identity/api/v1/project_group.py
spaceone/identity/api/v1/provider.py
spaceone/identity/api/v1/role.py
spaceone/identity/api/v1/role_binding.py
spaceone/identity/api/v1/service_account.py
spaceone/identity/api/v1/token.py
spaceone/identity/api/v1/user.py
spaceone/identity/conf/__init__.py
spaceone/identity/conf/global_conf.py
spaceone/identity/conf/permissions_conf.py
spaceone/identity/conf/proto_conf.py
spaceone/identity/conf/provider_conf.py
spaceone/identity/connector/__init__.py
spaceone/identity/connector/auth_plugin_connector.py
spaceone/identity/error/__init__.py
spaceone/identity/error/custom.py
spaceone/identity/error/error_authentication.py
spaceone/identity/error/error_domain.py
spaceone/identity/error/error_project.py
spaceone/identity/error/error_role.py
spaceone/identity/error/error_user.py
spaceone/identity/info/__init__.py
spaceone/identity/info/api_key_info.py
spaceone/identity/info/authorization_info.py
spaceone/identity/info/common_info.py
spaceone/identity/info/domain_info.py
spaceone/identity/info/domain_owner_info.py
spaceone/identity/info/endpoint_info.py
spaceone/identity/info/find_user_info.py
spaceone/identity/info/policy_info.py
spaceone/identity/info/project_group_info.py
spaceone/identity/info/project_info.py
spaceone/identity/info/provider_info.py
spaceone/identity/info/role_binding_info.py
spaceone/identity/info/role_info.py
spaceone/identity/info/service_account_info.py
spaceone/identity/info/token_info.py
spaceone/identity/info/user_info.py
spaceone/identity/lib/__init__.py
spaceone/identity/lib/cipher.py
spaceone/identity/lib/key_generator.py
cloudforet_identity-1.1.1.dist-info/METADATA
cloudforet_identity-1.1.1.dist-info/WHEEL
cloudforet_identity-1.1.1.dist-info/top_level.txt
cloudforet_identity-1.1.1.dist-info/RECORD
