Metadata-Version: 2.1
Name: cloudforet-identity
Version: 1.1.1
Summary: SpaceONE identity service
Home-page: https://www.spaceone.dev/
Author: MEGAZONE SpaceONE Team
Author-email: admin@spaceone.dev
License: Apache License 2.0
Platform: UNKNOWN
Requires-Dist: spaceone-core
Requires-Dist: spaceone-api
Requires-Dist: mongoengine
Requires-Dist: langcodes
Requires-Dist: bcrypt
Requires-Dist: redis
Requires-Dist: jinja2
Requires-Dist: fakeredis
Requires-Dist: mongomock
Requires-Dist: pytz
